ndx_labmetadata_abf/__init__.py
ndx_labmetadata_abf/test.py
ndx_labmetadata_abf-0.1.1.dist-info/LICENSE
ndx_labmetadata_abf-0.1.1.dist-info/METADATA
ndx_labmetadata_abf-0.1.1.dist-info/WHEEL
ndx_labmetadata_abf-0.1.1.dist-info/top_level.txt
ndx_labmetadata_abf-0.1.1.dist-info/RECORD
