Metadata-Version: 2.1
Name: ndx-labmetadata-abf
Version: 0.1.1
Summary: LabMetaData extension.
Home-page: UNKNOWN
Author: Luiz Tauffer and Ben Dichter
Author-email: ben.dichter@gmail.com
License: UNKNOWN
Platform: UNKNOWN
Classifier: Intended Audience :: Developers
Classifier: Intended Audience :: Science/Research
Requires-Dist: pynwb (>=1.0.2)
